django_institutions/__init__.py
django_institutions/base.py
django_institutions/data.py
django_institutions/fields.py
django_institutions/serializer_fields.py
django_institutions/world_universities_and_domains.json
django_institutions-0.0.6.dist-info/LICENSE
django_institutions-0.0.6.dist-info/METADATA
django_institutions-0.0.6.dist-info/WHEEL
django_institutions-0.0.6.dist-info/top_level.txt
django_institutions-0.0.6.dist-info/RECORD
