Metadata-Version: 2.1
Name: django_institutions
Version: 0.0.6
Summary: A django app for institutions model fields
Author-email: Konstantine Tsafatinos <kosta.tsaf@gmail.com>
Project-URL: Homepage, https://github.com/iamzoltan/django-institutions
Project-URL: Issues, https://github.com/iamzoltan/django-institutions/issues
Classifier: Programming Language :: Python :: 3
Classifier: License :: OSI Approved :: MIT License
Classifier: Operating System :: OS Independent
Requires-Python: >=3.8
License-File: LICENSE
